odoo/addons/ssi_hr_payroll_batch_work_log/README.rst
odoo/addons/ssi_hr_payroll_batch_work_log/__init__.py
odoo/addons/ssi_hr_payroll_batch_work_log/__manifest__.py
odoo/addons/ssi_hr_payroll_batch_work_log/models/__init__.py
odoo/addons/ssi_hr_payroll_batch_work_log/models/hr_payslip_batch.py
odoo/addons/ssi_hr_payroll_batch_work_log/static/description/icon.png
odoo14_addon_ssi_hr_payroll_batch_work_log-14.0.1.0.2.dev1.dist-info/METADATA
odoo14_addon_ssi_hr_payroll_batch_work_log-14.0.1.0.2.dev1.dist-info/WHEEL
odoo14_addon_ssi_hr_payroll_batch_work_log-14.0.1.0.2.dev1.dist-info/top_level.txt
odoo14_addon_ssi_hr_payroll_batch_work_log-14.0.1.0.2.dev1.dist-info/RECORD
